autotype/__init__.py
autotype/autotype.py
autotype-1.0.0.dist-info/DESCRIPTION.rst
autotype-1.0.0.dist-info/METADATA
autotype-1.0.0.dist-info/RECORD
autotype-1.0.0.dist-info/WHEEL
autotype-1.0.0.dist-info/metadata.json
autotype-1.0.0.dist-info/top_level.txt
src/autotype.py
