Metadata-Version: 2.0
Name: autotype
Version: 1.0.0
Summary: A Unicode-friendly tool for faking key presses to type strings on X11.
Home-page: https://github.com/gemdude46/autotype
Author: Marley Adair (gemdude46)
Author-email: UNKNOWN
License: UNKNOWN
Keywords: x x11 xautomation automation
Platform: UNKNOWN
Requires-Python: >=3,<4
Requires-Dist: python3-xlib
